odoo/addons/project_task_recurring_activity/README.rst
odoo/addons/project_task_recurring_activity/__init__.py
odoo/addons/project_task_recurring_activity/__manifest__.py
odoo/addons/project_task_recurring_activity/data/recurring_activity.xml
odoo/addons/project_task_recurring_activity/i18n/es.po
odoo/addons/project_task_recurring_activity/i18n/it.po
odoo/addons/project_task_recurring_activity/i18n/project_task_recurring_activity.pot
odoo/addons/project_task_recurring_activity/models/__init__.py
odoo/addons/project_task_recurring_activity/models/project_task.py
odoo/addons/project_task_recurring_activity/models/project_task_recurrence.py
odoo/addons/project_task_recurring_activity/models/recurring_activity.py
odoo/addons/project_task_recurring_activity/readme/CONFIGURE.rst
odoo/addons/project_task_recurring_activity/readme/CONTRIBUTORS.rst
odoo/addons/project_task_recurring_activity/readme/DESCRIPTION.rst
odoo/addons/project_task_recurring_activity/readme/USAGE.rst
odoo/addons/project_task_recurring_activity/security/ir.model.access.csv
odoo/addons/project_task_recurring_activity/static/description/icon.png
odoo/addons/project_task_recurring_activity/static/description/index.html
odoo/addons/project_task_recurring_activity/tests/__init__.py
odoo/addons/project_task_recurring_activity/tests/test_project_recurrence.py
odoo/addons/project_task_recurring_activity/views/project_task.xml
odoo/addons/project_task_recurring_activity/views/recurring_activity.xml
odoo_addon_project_task_recurring_activity-16.0.1.0.0.3.dist-info/METADATA
odoo_addon_project_task_recurring_activity-16.0.1.0.0.3.dist-info/WHEEL
odoo_addon_project_task_recurring_activity-16.0.1.0.0.3.dist-info/top_level.txt
odoo_addon_project_task_recurring_activity-16.0.1.0.0.3.dist-info/RECORD
